[
	{
		"q": "How can I volunteer?",
		"a": "You can sign up to volunteer similar to signing up for a race, through runsignup.com!"
	},
	{
		"q": "What supplies are given at races?",
		"a": "We have volunteers at drink stations to help you stay hydrated during the race. We'll also have CNAs available to help if there are unexpected events."
	},
	{
		"q": "Will you ever do free races?",
		"a": "In the future we want to consider doing free races. These will likely be 5k races."
	},
	{
		"q": "How do I sign up for races?",
		"a": "We do registration through runsignup.com. You'll need to create a free account and then sign up for a race of your choice."
	},
	{
		"q": "How can we see the maps?",
		"a": "The maps are available on runsignup.com. Right click to open the image in a new tab if you'd like to zoom in."
	},
	{
		"q": "How can we get in contact if we have more questions?",
		"a": "Check out our <a href=\"https://paa.ge/greatwesternracing/en\">linktree</a>. We're happy to answer any questions you may still have!"
	}
]
